opthub_scorer/__init__.py
opthub_scorer/main.py
opthub_scorer-0.8.1.dist-info/LICENSE
opthub_scorer-0.8.1.dist-info/METADATA
opthub_scorer-0.8.1.dist-info/WHEEL
opthub_scorer-0.8.1.dist-info/entry_points.txt
opthub_scorer-0.8.1.dist-info/top_level.txt
opthub_scorer-0.8.1.dist-info/RECORD
