Metadata-Version: 2.1
Name: opthub-scorer
Version: 0.8.1
Summary: OptHub Scorer
Home-page: https://github.com/opthub-org/opthub-scorer
Author: Naoki Hamada
Author-email: hmkz@s101.xrea.com
License: MIT
Classifier: Development Status :: 2 - Pre-Alpha
Classifier: Environment :: Console
Classifier: Intended Audience :: Developers
Classifier: License :: OSI Approved :: MIT License
Classifier: Operating System :: POSIX
Classifier: Programming Language :: Python
Classifier: Programming Language :: Python :: 3
Classifier: Programming Language :: Python :: 3.6
Classifier: Programming Language :: Python :: 3.7
Classifier: Programming Language :: Python :: 3.8
Classifier: Programming Language :: Python :: 3.9
Classifier: Programming Language :: Python :: 3.10
Classifier: Topic :: Internet :: WWW/HTTP :: Site Management
Requires-Python: >=3.6
License-File: LICENSE
Requires-Dist: setuptools >=21.0.0
Requires-Dist: click >=3.0
Requires-Dist: PyYAML >=5.1
Requires-Dist: gql[all] >=2.0.0
Requires-Dist: docker >=4.2.0
Provides-Extra: develop
Requires-Dist: tox ; extra == 'develop'
